alibabacloud_docmind_api20220711/__init__.py
alibabacloud_docmind_api20220711/client.py
alibabacloud_docmind_api20220711/models/__init__.py
alibabacloud_docmind_api20220711/models/_aync_trade_document_package_extract_smart_app_request.py
alibabacloud_docmind_api20220711/models/_aync_trade_document_package_extract_smart_app_response.py
alibabacloud_docmind_api20220711/models/_aync_trade_document_package_extract_smart_app_response_body.py
alibabacloud_docmind_api20220711/models/_aync_trade_document_package_extract_smart_app_shrink_request.py
alibabacloud_docmind_api20220711/models/_get_doc_parser_result_request.py
alibabacloud_docmind_api20220711/models/_get_doc_parser_result_response.py
alibabacloud_docmind_api20220711/models/_get_doc_parser_result_response_body.py
alibabacloud_docmind_api20220711/models/_get_doc_structure_result_request.py
alibabacloud_docmind_api20220711/models/_get_doc_structure_result_response.py
alibabacloud_docmind_api20220711/models/_get_doc_structure_result_response_body.py
alibabacloud_docmind_api20220711/models/_get_document_compare_result_request.py
alibabacloud_docmind_api20220711/models/_get_document_compare_result_response.py
alibabacloud_docmind_api20220711/models/_get_document_compare_result_response_body.py
alibabacloud_docmind_api20220711/models/_get_document_convert_result_request.py
alibabacloud_docmind_api20220711/models/_get_document_convert_result_response.py
alibabacloud_docmind_api20220711/models/_get_document_convert_result_response_body.py
alibabacloud_docmind_api20220711/models/_get_document_extract_result_request.py
alibabacloud_docmind_api20220711/models/_get_document_extract_result_response.py
alibabacloud_docmind_api20220711/models/_get_document_extract_result_response_body.py
alibabacloud_docmind_api20220711/models/_get_page_num_request.py
alibabacloud_docmind_api20220711/models/_get_page_num_response.py
alibabacloud_docmind_api20220711/models/_get_page_num_response_body.py
alibabacloud_docmind_api20220711-1.4.12.dist-info/LICENSE
alibabacloud_docmind_api20220711-1.4.12.dist-info/METADATA
alibabacloud_docmind_api20220711-1.4.12.dist-info/WHEEL
alibabacloud_docmind_api20220711-1.4.12.dist-info/top_level.txt
alibabacloud_docmind_api20220711-1.4.12.dist-info/RECORD
